django_remote_debug/__init__.py
django_remote_debug/management/__init__.py
django_remote_debug/management/commands/__init__.py
django_remote_debug/management/commands/runserver.py
django_remote_debug-0.0.2.dist-info/LICENSE
django_remote_debug-0.0.2.dist-info/METADATA
django_remote_debug-0.0.2.dist-info/WHEEL
django_remote_debug-0.0.2.dist-info/top_level.txt
django_remote_debug-0.0.2.dist-info/RECORD
