Metadata-Version: 2.1
Name: django-remote-debug
Version: 0.0.2
Summary: A Wrapper to Visual Studio remote debugging server for python
Home-page: https://github.com/p1c2u/django-remote-debug
Author: Artur Maciag
Author-email: maciag.artur@gmail.com
License: MIT
Platform: UNKNOWN
Classifier: Development Status :: 4 - Beta
Classifier: Intended Audience :: Developers
Classifier: Topic :: Software Development :: Libraries :: Python Modules
Classifier: Operating System :: OS Independent
Classifier: Programming Language :: Python :: 2.7
Classifier: Programming Language :: Python :: 3.4
Classifier: Programming Language :: Python :: 3.5
Classifier: Programming Language :: Python :: 3.6
Classifier: Programming Language :: Python :: 3.7
Requires-Dist: ptvsd (>=4.0.0)
